odoo10_addon_delivery_carrier_label_postlogistics-10.0.1.2.1-py3.8-nspkg.pth
odoo/addons/delivery_carrier_label_postlogistics/README.rst
odoo/addons/delivery_carrier_label_postlogistics/__init__.py
odoo/addons/delivery_carrier_label_postlogistics/__manifest__.py
odoo/addons/delivery_carrier_label_postlogistics/data/barcode_v2_1.wsdl
odoo/addons/delivery_carrier_label_postlogistics/data/barcode_v2_1.xsd
odoo/addons/delivery_carrier_label_postlogistics/data/barcode_v2_2.wsdl
odoo/addons/delivery_carrier_label_postlogistics/data/barcode_v2_2.xsd
odoo/addons/delivery_carrier_label_postlogistics/data/delivery.xml
odoo/addons/delivery_carrier_label_postlogistics/data/partner.xml
odoo/addons/delivery_carrier_label_postlogistics/data/post-barcode-handbuch.pdf
odoo/addons/delivery_carrier_label_postlogistics/data/product.xml
odoo/addons/delivery_carrier_label_postlogistics/data/integration/barcode_v2_2_wsbc.wsdl
odoo/addons/delivery_carrier_label_postlogistics/data/integration/barcode_v2_2_wsbc.xsd
odoo/addons/delivery_carrier_label_postlogistics/data/production/barcode_v2_2_wsbc.wsdl
odoo/addons/delivery_carrier_label_postlogistics/data/production/barcode_v2_2_wsbc.xsd
odoo/addons/delivery_carrier_label_postlogistics/i18n/am.po
odoo/addons/delivery_carrier_label_postlogistics/i18n/ar.po
odoo/addons/delivery_carrier_label_postlogistics/i18n/ca.po
odoo/addons/delivery_carrier_label_postlogistics/i18n/cs.po
odoo/addons/delivery_carrier_label_postlogistics/i18n/de.po
odoo/addons/delivery_carrier_label_postlogistics/i18n/delivery_carrier_label_postlogistics.pot
odoo/addons/delivery_carrier_label_postlogistics/i18n/el_GR.po
odoo/addons/delivery_carrier_label_postlogistics/i18n/es.po
odoo/addons/delivery_carrier_label_postlogistics/i18n/es_CR.po
odoo/addons/delivery_carrier_label_postlogistics/i18n/es_EC.po
odoo/addons/delivery_carrier_label_postlogistics/i18n/es_ES.po
odoo/addons/delivery_carrier_label_postlogistics/i18n/es_MX.po
odoo10_addon_delivery_carrier_label_postlogistics-10.0.1.2.1.dist-info/METADATA
odoo10_addon_delivery_carrier_label_postlogistics-10.0.1.2.1.dist-info/WHEEL
odoo10_addon_delivery_carrier_label_postlogistics-10.0.1.2.1.dist-info/namespace_packages.txt
odoo10_addon_delivery_carrier_label_postlogistics-10.0.1.2.1.dist-info/top_level.txt
odoo10_addon_delivery_carrier_label_postlogistics-10.0.1.2.1.dist-info/RECORD
