Metadata-Version: 2.1
Name: odoo10-addon-delivery-carrier-label-postlogistics
Version: 10.0.1.2.1
Summary: Print postlogistics shipping labels
Home-page: https://github.com/OCA/delivery-carrier
Author: Camptocamp,Odoo Community Association (OCA)
Author-email: support@odoo-community.org
License: AGPL-3
Platform: UNKNOWN
Classifier: Programming Language :: Python
Classifier: Framework :: Odoo
Classifier: Framework :: Odoo :: 10.0
Classifier: License :: OSI Approved :: GNU Affero General Public License v3
Requires-Python: ~=2.7
Requires-Dist: odoo10-addon-base-delivery-carrier-label
Requires-Dist: odoo10-addon-configuration-helper
Requires-Dist: odoo10-addon-web-domain-field
Requires-Dist: odoo (<10.1dev,>=10.0)
Requires-Dist: suds-jurko
